Workbook

Sheet Pricer
A1: Asia Digital Bridge Note: 7Y USD 100% capital-protected note on a 10% vol-target index
A2: Blue = input (edit these), black = formula, green = link to another sheet. Yellow = key assumption to verify on Bloomberg as of 17 Sep 2026.
A4: Inputs | B4: Value | D4: Tenor | E4: USD funding
A5: Notional (USD) | B5: 100000000 | D5: 1 | E5: 0.0478
A6: Tenor (years) | B6: 7 | D6: 2 | E6: 0.053
A7: Capital protection at maturity | B7: 1 | D7: 3 | E7: 0.0552
A8: Issuer fee / margin (upfront) | B8: 0.02 | D8: 5 | E8: 0.0569
A9: USD rate for option pricing (OIS) | B9: 0.0375 | D9: 7 | E9: 0.0575
A10: VT index: target volatility | B10: 0.1 | D10: 10 | E10: 0.0582
A11: VT index: decrement p.a. | B11: 0.01 | D11: 20 | E11: 0.0604
A12: MC / Black-Scholes price ratio | B12: 0.96073211 | D12: Source: 2026 game rules, Natixis funding grid (USD).
A14: Pricing | B14: Value
A15: Interpolated USD funding rate | B15: =IF($B$6>=MAX($D$5:$D$11),INDEX($E$5:$E$11,ROWS($D$5:$D$11)),INDEX($E$5:$E$11,MATCH($B$6,$D$5:$D$11,1))+(INDEX($E$5:$E$11,MATCH($B$6,$D$5:$D$11,1)+1)-INDEX($E$5:$E$11,MATCH($B$6,$D$5:$D$11,1)))*($B$6-INDEX($D$5:$D$11,MATCH($B$6,$D$5:$D$11,1)))/(INDEX($D$5:$D$11,MATCH($B$6,$D$5:$D$11,1)+1)-INDEX($D$5:$D$11,MATCH($B$6,$D$5:$D$11,1)))) | G15: Linear interpolation on the grid (rules, footnote 1)
A16: Zero-coupon bond price (% notional) | B16: =$B$7/(1+B15)^$B$6 | G16: Protection / (1 + funding)^T
A17: Option budget (% notional) | B17: =1-B16-$B$8 | G17: 100% - bond - fee
A18: BS d1 | B18: =(($B$9-$B$11)+0.5*$B$10^2)*$B$6/($B$10*SQRT($B$6)) | G18: VT index forward drifts at r - decrement
A19: BS d2 | B19: =B18-$B$10*SQRT($B$6)
A20: ATM call on VT index, Black-Scholes (% notional) | B20: =EXP(-$B$11*$B$6)*NORMSDIST(B18)-EXP(-$B$9*$B$6)*NORMSDIST(B19)
A21: ATM call on VT index, MC-adjusted | B21: =B20*$B$12 | G21: Captures vol-target lag / gap risk
A22: Participation (Black-Scholes) | B22: =IF(B20>0,B17/B20,0)
A23: PARTICIPATION (MC-adjusted, quoted) | B23: =IF(B21>0,B17/B21,0) | G23: Headline term for the term sheet
A24: Bond leg (USD) | B24: =$B$5*B16
A25: Option leg (USD) | B25: =$B$5*B17
A26: Issuer fee (USD) | B26: =$B$5*$B$8
A27: Check: legs sum to notional | B27: =IF(ABS(B24+B25+B26-$B$5)<1,"OK","CHECK")

Sheet Payoff
A1: Redemption at maturity vs VT index performance
A2: Participation and protection link to the Pricer sheet. Direct basket shown for a VT-index move only (illustrative).
A3: Participation | B3: =Pricer!B23 | C3: Protection | D3: =Pricer!B7
A4: Tenor (years) | B4: =Pricer!B6
A6: VT index performance | B6: Redemption (% notional) | C6: Annualised return | D6: Payout (USD) | E6: Gain vs notional (USD)
A7: -0.4 | B7: =$D$3+$B$3*MAX(0,A7) | C7: =B7^(1/$B$4)-1 | D7: =B7*Pricer!$B$5 | E7: =D7-Pricer!$B$5
A8: -0.2 | B8: =$D$3+$B$3*MAX(0,A8) | C8: =B8^(1/$B$4)-1 | D8: =B8*Pricer!$B$5 | E8: =D8-Pricer!$B$5
A9: -0.1 | B9: =$D$3+$B$3*MAX(0,A9) | C9: =B9^(1/$B$4)-1 | D9: =B9*Pricer!$B$5 | E9: =D9-Pricer!$B$5
A10: 0 | B10: =$D$3+$B$3*MAX(0,A10) | C10: =B10^(1/$B$4)-1 | D10: =B10*Pricer!$B$5 | E10: =D10-Pricer!$B$5
A11: 0.1 | B11: =$D$3+$B$3*MAX(0,A11) | C11: =B11^(1/$B$4)-1 | D11: =B11*Pricer!$B$5 | E11: =D11-Pricer!$B$5
A12: 0.2 | B12: =$D$3+$B$3*MAX(0,A12) | C12: =B12^(1/$B$4)-1 | D12: =B12*Pricer!$B$5 | E12: =D12-Pricer!$B$5
A13: 0.3 | B13: =$D$3+$B$3*MAX(0,A13) | C13: =B13^(1/$B$4)-1 | D13: =B13*Pricer!$B$5 | E13: =D13-Pricer!$B$5
A14: 0.5 | B14: =$D$3+$B$3*MAX(0,A14) | C14: =B14^(1/$B$4)-1 | D14: =B14*Pricer!$B$5 | E14: =D14-Pricer!$B$5
A15: 0.75 | B15: =$D$3+$B$3*MAX(0,A15) | C15: =B15^(1/$B$4)-1 | D15: =B15*Pricer!$B$5 | E15: =D15-Pricer!$B$5
A16: 1 | B16: =$D$3+$B$3*MAX(0,A16) | C16: =B16^(1/$B$4)-1 | D16: =B16*Pricer!$B$5 | E16: =D16-Pricer!$B$5
A17: 1.5 | B17: =$D$3+$B$3*MAX(0,A17) | C17: =B17^(1/$B$4)-1 | D17: =B17*Pricer!$B$5 | E17: =D17-Pricer!$B$5

Sheet Design Dial
A1: Participation by index design (Black-Scholes x MC ratio; links to Pricer)
A2: Higher decrement lowers the index forward and buys a bigger headline participation, but adds drag. See MC Results for what the client actually receives.
A4: Target vol \ decrement | B4: 0 | C4: 0.01 | D4: 0.02 | E4: 0.03 | F4: 0.04
A5: 0.08 | B5: =Pricer!$B$17/(EXP(-B$4*Pricer!$B$6)*NORMSDIST(((Pricer!$B$9-B$4)+0.5*$A5^2)*Pricer!$B$6/($A5*SQRT(Pricer!$B$6)))-EXP(-Pricer!$B$9*Pricer!$B$6)*NORMSDIST(((Pricer!$B$9-B$4)+0.5*$A5^2)*Pricer!$B$6/($A5*SQRT(Pricer!$B$6))-$A5*SQRT(Pricer!$B$6)))*Pricer!$B$12 | C5: =Pricer!$B$17/(EXP(-C$4*Pricer!$B$6)*NORMSDIST(((Pricer!$B$9-C$4)+0.5*$A5^2)*Pricer!$B$6/($A5*SQRT(Pricer!$B$6)))-EXP(-Pricer!$B$9*Pricer!$B$6)*NORMSDIST(((Pricer!$B$9-C$4)+0.5*$A5^2)*Pricer!$B$6/($A5*SQRT(Pricer!$B$6))-$A5*SQRT(Pricer!$B$6)))*Pricer!$B$12 | D5: =Pricer!$B$17/(EXP(-D$4*Pricer!$B$6)*NORMSDIST(((Pricer!$B$9-D$4)+0.5*$A5^2)*Pricer!$B$6/($A5*SQRT(Pricer!$B$6)))-EXP(-Pricer!$B$9*Pricer!$B$6)*NORMSDIST(((Pricer!$B$9-D$4)+0.5*$A5^2)*Pricer!$B$6/($A5*SQRT(Pricer!$B$6))-$A5*SQRT(Pricer!$B$6)))*Pricer!$B$12 | E5: =Pricer!$B$17/(EXP(-E$4*Pricer!$B$6)*NORMSDIST(((Pricer!$B$9-E$4)+0.5*$A5^2)*Pricer!$B$6/($A5*SQRT(Pricer!$B$6)))-EXP(-Pricer!$B$9*Pricer!$B$6)*NORMSDIST(((Pricer!$B$9-E$4)+0.5*$A5^2)*Pricer!$B$6/($A5*SQRT(Pricer!$B$6))-$A5*SQRT(Pricer!$B$6)))*Pricer!$B$12 | F5: =Pricer!$B$17/(EXP(-F$4*Pricer!$B$6)*NORMSDIST(((Pricer!$B$9-F$4)+0.5*$A5^2)*Pricer!$B$6/($A5*SQRT(Pricer!$B$6)))-EXP(-Pricer!$B$9*Pricer!$B$6)*NORMSDIST(((Pricer!$B$9-F$4)+0.5*$A5^2)*Pricer!$B$6/($A5*SQRT(Pricer!$B$6))-$A5*SQRT(Pricer!$B$6)))*Pricer!$B$12
A6: 0.1 | B6: =Pricer!$B$17/(EXP(-B$4*Pricer!$B$6)*NORMSDIST(((Pricer!$B$9-B$4)+0.5*$A6^2)*Pricer!$B$6/($A6*SQRT(Pricer!$B$6)))-EXP(-Pricer!$B$9*Pricer!$B$6)*NORMSDIST(((Pricer!$B$9-B$4)+0.5*$A6^2)*Pricer!$B$6/($A6*SQRT(Pricer!$B$6))-$A6*SQRT(Pricer!$B$6)))*Pricer!$B$12 | C6: =Pricer!$B$17/(EXP(-C$4*Pricer!$B$6)*NORMSDIST(((Pricer!$B$9-C$4)+0.5*$A6^2)*Pricer!$B$6/($A6*SQRT(Pricer!$B$6)))-EXP(-Pricer!$B$9*Pricer!$B$6)*NORMSDIST(((Pricer!$B$9-C$4)+0.5*$A6^2)*Pricer!$B$6/($A6*SQRT(Pricer!$B$6))-$A6*SQRT(Pricer!$B$6)))*Pricer!$B$12 | D6: =Pricer!$B$17/(EXP(-D$4*Pricer!$B$6)*NORMSDIST(((Pricer!$B$9-D$4)+0.5*$A6^2)*Pricer!$B$6/($A6*SQRT(Pricer!$B$6)))-EXP(-Pricer!$B$9*Pricer!$B$6)*NORMSDIST(((Pricer!$B$9-D$4)+0.5*$A6^2)*Pricer!$B$6/($A6*SQRT(Pricer!$B$6))-$A6*SQRT(Pricer!$B$6)))*Pricer!$B$12 | E6: =Pricer!$B$17/(EXP(-E$4*Pricer!$B$6)*NORMSDIST(((Pricer!$B$9-E$4)+0.5*$A6^2)*Pricer!$B$6/($A6*SQRT(Pricer!$B$6)))-EXP(-Pricer!$B$9*Pricer!$B$6)*NORMSDIST(((Pricer!$B$9-E$4)+0.5*$A6^2)*Pricer!$B$6/($A6*SQRT(Pricer!$B$6))-$A6*SQRT(Pricer!$B$6)))*Pricer!$B$12 | F6: =Pricer!$B$17/(EXP(-F$4*Pricer!$B$6)*NORMSDIST(((Pricer!$B$9-F$4)+0.5*$A6^2)*Pricer!$B$6/($A6*SQRT(Pricer!$B$6)))-EXP(-Pricer!$B$9*Pricer!$B$6)*NORMSDIST(((Pricer!$B$9-F$4)+0.5*$A6^2)*Pricer!$B$6/($A6*SQRT(Pricer!$B$6))-$A6*SQRT(Pricer!$B$6)))*Pricer!$B$12
A7: 0.12 | B7: =Pricer!$B$17/(EXP(-B$4*Pricer!$B$6)*NORMSDIST(((Pricer!$B$9-B$4)+0.5*$A7^2)*Pricer!$B$6/($A7*SQRT(Pricer!$B$6)))-EXP(-Pricer!$B$9*Pricer!$B$6)*NORMSDIST(((Pricer!$B$9-B$4)+0.5*$A7^2)*Pricer!$B$6/($A7*SQRT(Pricer!$B$6))-$A7*SQRT(Pricer!$B$6)))*Pricer!$B$12 | C7: =Pricer!$B$17/(EXP(-C$4*Pricer!$B$6)*NORMSDIST(((Pricer!$B$9-C$4)+0.5*$A7^2)*Pricer!$B$6/($A7*SQRT(Pricer!$B$6)))-EXP(-Pricer!$B$9*Pricer!$B$6)*NORMSDIST(((Pricer!$B$9-C$4)+0.5*$A7^2)*Pricer!$B$6/($A7*SQRT(Pricer!$B$6))-$A7*SQRT(Pricer!$B$6)))*Pricer!$B$12 | D7: =Pricer!$B$17/(EXP(-D$4*Pricer!$B$6)*NORMSDIST(((Pricer!$B$9-D$4)+0.5*$A7^2)*Pricer!$B$6/($A7*SQRT(Pricer!$B$6)))-EXP(-Pricer!$B$9*Pricer!$B$6)*NORMSDIST(((Pricer!$B$9-D$4)+0.5*$A7^2)*Pricer!$B$6/($A7*SQRT(Pricer!$B$6))-$A7*SQRT(Pricer!$B$6)))*Pricer!$B$12 | E7: =Pricer!$B$17/(EXP(-E$4*Pricer!$B$6)*NORMSDIST(((Pricer!$B$9-E$4)+0.5*$A7^2)*Pricer!$B$6/($A7*SQRT(Pricer!$B$6)))-EXP(-Pricer!$B$9*Pricer!$B$6)*NORMSDIST(((Pricer!$B$9-E$4)+0.5*$A7^2)*Pricer!$B$6/($A7*SQRT(Pricer!$B$6))-$A7*SQRT(Pricer!$B$6)))*Pricer!$B$12 | F7: =Pricer!$B$17/(EXP(-F$4*Pricer!$B$6)*NORMSDIST(((Pricer!$B$9-F$4)+0.5*$A7^2)*Pricer!$B$6/($A7*SQRT(Pricer!$B$6)))-EXP(-Pricer!$B$9*Pricer!$B$6)*NORMSDIST(((Pricer!$B$9-F$4)+0.5*$A7^2)*Pricer!$B$6/($A7*SQRT(Pricer!$B$6))-$A7*SQRT(Pricer!$B$6)))*Pricer!$B$12
A8: 0.15 | B8: =Pricer!$B$17/(EXP(-B$4*Pricer!$B$6)*NORMSDIST(((Pricer!$B$9-B$4)+0.5*$A8^2)*Pricer!$B$6/($A8*SQRT(Pricer!$B$6)))-EXP(-Pricer!$B$9*Pricer!$B$6)*NORMSDIST(((Pricer!$B$9-B$4)+0.5*$A8^2)*Pricer!$B$6/($A8*SQRT(Pricer!$B$6))-$A8*SQRT(Pricer!$B$6)))*Pricer!$B$12 | C8: =Pricer!$B$17/(EXP(-C$4*Pricer!$B$6)*NORMSDIST(((Pricer!$B$9-C$4)+0.5*$A8^2)*Pricer!$B$6/($A8*SQRT(Pricer!$B$6)))-EXP(-Pricer!$B$9*Pricer!$B$6)*NORMSDIST(((Pricer!$B$9-C$4)+0.5*$A8^2)*Pricer!$B$6/($A8*SQRT(Pricer!$B$6))-$A8*SQRT(Pricer!$B$6)))*Pricer!$B$12 | D8: =Pricer!$B$17/(EXP(-D$4*Pricer!$B$6)*NORMSDIST(((Pricer!$B$9-D$4)+0.5*$A8^2)*Pricer!$B$6/($A8*SQRT(Pricer!$B$6)))-EXP(-Pricer!$B$9*Pricer!$B$6)*NORMSDIST(((Pricer!$B$9-D$4)+0.5*$A8^2)*Pricer!$B$6/($A8*SQRT(Pricer!$B$6))-$A8*SQRT(Pricer!$B$6)))*Pricer!$B$12 | E8: =Pricer!$B$17/(EXP(-E$4*Pricer!$B$6)*NORMSDIST(((Pricer!$B$9-E$4)+0.5*$A8^2)*Pricer!$B$6/($A8*SQRT(Pricer!$B$6)))-EXP(-Pricer!$B$9*Pricer!$B$6)*NORMSDIST(((Pricer!$B$9-E$4)+0.5*$A8^2)*Pricer!$B$6/($A8*SQRT(Pricer!$B$6))-$A8*SQRT(Pricer!$B$6)))*Pricer!$B$12 | F8: =Pricer!$B$17/(EXP(-F$4*Pricer!$B$6)*NORMSDIST(((Pricer!$B$9-F$4)+0.5*$A8^2)*Pricer!$B$6/($A8*SQRT(Pricer!$B$6)))-EXP(-Pricer!$B$9*Pricer!$B$6)*NORMSDIST(((Pricer!$B$9-F$4)+0.5*$A8^2)*Pricer!$B$6/($A8*SQRT(Pricer!$B$6))-$A8*SQRT(Pricer!$B$6)))*Pricer!$B$12

Sheet MC Results
A1: Monte Carlo outputs (values pasted from pricing/scenario2_vt_note.py)
A2: Placeholder market inputs (regime vol 27%/50%, OIS 3.75%, raw-basket implied vol 33%). Forward simulation, NOT a historical backtest.
A4: Feature menu (same simulated paths)
A5: Feature | B5: Option cost | C5: Participation
A6: Base: uncapped call | B6: 0.18605393 | C6: 1.6331762
A7: + 12M final averaging | B7: 0.17417993 | C7: 1.7445113
A8: + Legacy Lock 130/160/190 | B8: 0.19606635 | C8: 1.5497756
A9: + Lock + averaging | B9: 0.18242768 | C9: 1.6656401
A11: The decrement trap: headline vs outcome
A12: Index design | B12: Participation | C12: Median @6% | D12: P(only 100 back) @6% | E12: Median @9% | F12: P(only 100 back) @9%
A13: Max-headline (12% / 4%) | B13: 3.5121861 | C13: 1.0007884 | D13: 0.4993 | E13: 1.3135672 | F13: 0.3956
A14: 10% / 2% | B14: 2.1406704 | C14: 1.3314067 | D14: 0.2902 | E14: 1.5136635 | F14: 0.2043
A15: Recommended (10% / 1%) | B15: 1.6001533 | C15: 1.3817018 | D15: 0.2056 | E15: 1.5278104 | F15: 0.1383
A16: No decrement (10% / 0%) | B16: 1.2339376 | C16: 1.4051434 | D16: 0.1385 | E16: 1.5259766 | F16: 0.0873
A17: Raw basket, no vol target | B17: 0.88710881 | C17: 1.1002876 | D17: 0.4506 | E17: 1.3310205 | F17: 0.3448
A19: Real-world outcomes at 7Y (multiple of capital)
A20: Basket return / product | B20: Mean | C20: 5th pct | D20: Median | E20: 95th pct | F20: Median CAGR | G20: P(below 100) | H20: P(100 or less)
A21: 3% p.a. | VT note | B21: 1.3788569 | C21: 1 | D21: 1.2445871 | E21: 2.2505859 | F21: 0.031751345 | G21: 0 | H21: 0.29715
A22: 3% p.a. | Protected note on raw basket | B22: 1.422897 | C22: 1 | D22: 1 | E22: 3.0719161 | F22: 0 | G22: 0 | H22: 0.5573
A23: 3% p.a. | Direct basket | B23: 1.2331844 | C23: 0.23701516 | D23: 0.89218546 | E23: 3.3355828 | F23: -0.016165238 | G23: 0.5572 | H23: 0.5573
A24: 6% p.a. | VT note | B24: 1.4966055 | C24: 1 | D24: 1.3823983 | E24: 2.4635095 | F24: 0.047346672 | G24: 0 | H24: 0.2073
A25: 6% p.a. | Protected note on raw basket | B25: 1.6238641 | C25: 1 | D25: 1.0893049 | E25: 3.7633753 | F25: 0.012294941 | G25: 0 | H25: 0.4542
A26: 6% p.a. | Direct basket | B26: 1.5213526 | C26: 0.29240041 | D26: 1.1006696 | E26: 4.1150353 | F26: 0.013796991 | G26: 0.45405 | H26: 0.4542
A27: 9% p.a. | VT note | B27: 1.6324148 | C27: 1 | D27: 1.5316009 | E27: 2.6889989 | F27: 0.062794679 | G27: 0 | H27: 0.1406
A28: 9% p.a. | Protected note on raw basket | B28: 1.8932994 | C28: 1 | D28: 1.3174714 | E28: 4.6164133 | F28: 0.040173737 | G28: 0 | H28: 0.35185
A29: 9% p.a. | Direct basket | B29: 1.8768593 | C29: 0.36072797 | D29: 1.357872 | E29: 5.0766288 | F29: 0.044671706 | G29: 0.35175 | H29: 0.35185
A31: 7Y UST proxy multiple: 1.38x. Mean VT exposure 34%; realised index vol 9.8%.

Sheet Risk
A1: Unit 15 risk section: VaR/ES, stress, sizing
A3: Note fair value at issue (% notional) | B3: 0.98
A4: Delta: note change per 1% move in VT index | B4: 0.011776826
A5: DV01: note change per +1bp rates | B5: 0.00016451656
A6: 10-day 99% VaR (delta-normal, % notional) | B6: 0.055048868
A7: 10-day 99% Expected Shortfall (% notional) | B7: 0.063128031
A8: 10-day 99% VaR (USD) | B8: =B6*Pricer!$B$5
A9: Family net worth (USD) | B9: 2000000000
A10: Stress (spot, vol and rates shocked together) | B10: VT index level | C10: Rate shift | D10: Note MTM | E10: MTM P&L (USD) | F10: % of net worth
A11: AI hardware crash: basket -30% in 1M, vol 27%->50%, rates -50bp | B11: 0.90555556 | C11: -0.005 | D11: 0.87519149 | E11: =(D11-$B$3)*Pricer!$B$5 | F11: =E11/$B$9
A12: Taiwan gap: basket -20% overnight, rates unchanged | B12: 0.92592593 | C12: 0 | D12: 0.89738918 | E12: =(D12-$B$3)*Pricer!$B$5 | F12: =E12/$B$9
A13: Stagflation: basket -15%, rates +100bp | B13: 0.94444444 | C13: 0.01 | D13: 0.93065652 | E13: =(D13-$B$3)*Pricer!$B$5 | F13: =E13/$B$9
A14: Bull: basket +25%, rates -50bp | B14: 1.0925926 | C14: -0.005 | D14: 1.0829408 | E14: =(D14-$B$3)*Pricer!$B$5 | F14: =E14/$B$9
A16: Sizing identity (Unit 15)
A17: Allocation as % of net worth | B17: =Pricer!B5/B9
A18: Contractual max loss at maturity (ex issuer default) | B18: =1-Pricer!B7
A19: Worst stress MTM loss (USD) = notional x (fair value - worst MTM) | B19: =-MIN(E11:E14)
A20: Worst stress MTM loss as % of net worth | B20: =B19/B9
A22: Exits: (1) profit target: sell back on the issuer bid once the index is up 60%; (2) no stop-loss on a protected note, the floor is the stop; (3) thesis invalidation: Taiwan blockade or sweeping chip export bans; (4) time: hold to maturity.

Sheet Basket
A1: Underlying basket: Asian AI-hardware leaders (equal weight, USD quanto)
A2: Fill the yellow columns from Bloomberg (CUR_MKT_CAP in USD Mn; 6M average daily traded value in USD Mn). Example values in row 5 are illustrative only.
A4: Bloomberg | B4: Name | C4: Country | D4: Theme | E4: Weight | F4: Mkt cap USD Mn | G4: 6M ADV USD Mn | H4: Eligible?
A5: 2330 TT | B5: TSMC | C5: TW | D5: Foundry / AI accelerators | E5: =1/COUNTA($A$5:$A$17) | F5: 950000 | G5: 4000 | H5: =IF(OR(F5="",G5=""),"fill",IF(AND(F5>=250,G5>=5),"OK","FAIL"))
A6: 2454 TT | B6: MediaTek | C6: TW | D6: Custom AI ASICs / edge AI | E6: =1/COUNTA($A$5:$A$17) | H6: =IF(OR(F6="",G6=""),"fill",IF(AND(F6>=250,G6>=5),"OK","FAIL"))
A7: 000660 KS | B7: SK Hynix | C7: KR | D7: HBM memory | E7: =1/COUNTA($A$5:$A$17) | H7: =IF(OR(F7="",G7=""),"fill",IF(AND(F7>=250,G7>=5),"OK","FAIL"))
A8: 005930 KS | B8: Samsung Electronics | C8: KR | D8: HBM / memory | E8: =1/COUNTA($A$5:$A$17) | H8: =IF(OR(F8="",G8=""),"fill",IF(AND(F8>=250,G8>=5),"OK","FAIL"))
A9: 8035 JT | B9: Tokyo Electron | C9: JP | D9: Wafer-fab equipment | E9: =1/COUNTA($A$5:$A$17) | H9: =IF(OR(F9="",G9=""),"fill",IF(AND(F9>=250,G9>=5),"OK","FAIL"))
A10: 6857 JT | B10: Advantest | C10: JP | D10: AI chip testing | E10: =1/COUNTA($A$5:$A$17) | H10: =IF(OR(F10="",G10=""),"fill",IF(AND(F10>=250,G10>=5),"OK","FAIL"))
A11: 6146 JT | B11: Disco | C11: JP | D11: Dicing / grinding for HBM | E11: =1/COUNTA($A$5:$A$17) | H11: =IF(OR(F11="",G11=""),"fill",IF(AND(F11>=250,G11>=5),"OK","FAIL"))
A12: 4063 JT | B12: Shin-Etsu Chemical | C12: JP | D12: Silicon wafers / materials | E12: =1/COUNTA($A$5:$A$17) | H12: =IF(OR(F12="",G12=""),"fill",IF(AND(F12>=250,G12>=5),"OK","FAIL"))
A13: 3711 TT | B13: ASE Technology | C13: TW | D13: Advanced packaging | E13: =1/COUNTA($A$5:$A$17) | H13: =IF(OR(F13="",G13=""),"fill",IF(AND(F13>=250,G13>=5),"OK","FAIL"))
A14: 4062 JT | B14: Ibiden | C14: JP | D14: AI chip substrates | E14: =1/COUNTA($A$5:$A$17) | H14: =IF(OR(F14="",G14=""),"fill",IF(AND(F14>=250,G14>=5),"OK","FAIL"))
A15: 2317 TT | B15: Hon Hai (Foxconn) | C15: TW | D15: AI server assembly | E15: =1/COUNTA($A$5:$A$17) | H15: =IF(OR(F15="",G15=""),"fill",IF(AND(F15>=250,G15>=5),"OK","FAIL"))
A16: 2382 TT | B16: Quanta Computer | C16: TW | D16: AI servers | E16: =1/COUNTA($A$5:$A$17) | H16: =IF(OR(F16="",G16=""),"fill",IF(AND(F16>=250,G16>=5),"OK","FAIL"))
A17: 2308 TT | B17: Delta Electronics | C17: TW | D17: Data-centre power / cooling | E17: =1/COUNTA($A$5:$A$17) | H17: =IF(OR(F17="",G17=""),"fill",IF(AND(F17>=250,G17>=5),"OK","FAIL"))
A18: Total weight | E18: =SUM(E5:E17)
A20: Excluded on purpose: data-centre operators/REITs, telecom towers, renewables, real estate (overlap with family businesses); names on US restriction lists (e.g. SMIC). Rules: market cap >= USD 250M; listed ADV > USD 5M over 6M; no OFAC-sanctioned countries; Bloomberg searchable.

Sheet Term Sheet
A1: Indicative term sheet (links to Pricer)
A3: Issuer | B3: Natixis (guaranteed by BPCE)
A4: Client | B4: NKE Private Wealth (Chak family office)
A5: Notional | B5: =TEXT(Pricer!B5,"$#,##0")
A6: Currency | B6: USD; underlying quanto (no FX exposure)
A7: Trade / issue date | B7: 17 Sep 2026
A8: Maturity | B8: ="Sep "&(2026+Pricer!B6)&" ("&Pricer!B6&"Y)"
A9: Underlying | B9: Natixis Asia Digital Bridge 10% VT Index (USD, 1% decrement), on an equal-weight basket of 13 Asian AI-hardware stocks
A10: Index rules | B10: Daily exposure = min(10% / max(20d, 60d realised vol), 150%), cash on the remainder, minus 1% p.a.
A11: Capital protection | B11: =TEXT(Pricer!B7,"0%")&" at maturity, subject to issuer credit"
A12: Participation | B12: =TEXT(Pricer!B23,"0%")&" of index performance, uncapped"
A13: Redemption | B13: Protection + Participation x max(0, Index final / Index initial - 1)
A14: Optional enhancements | B14: 12M final averaging (raises participation); Legacy Lock 130/160/190 (lowers it); see MC Results
A15: Appendix variant | B15: Best-of with a spot Bitcoin ETF sleeve (IBIT US); not in the core proposal
A16: Secondary market | B16: Natixis indicative daily bid, under normal market conditions
A17: Pricing basis | B17: Funding from the game-rules grid; option inputs are placeholders to be refreshed on Bloomberg
